[
    {
        "id": "633461c54a4408e1eb411ede",
        "image": "https://images.unsplash.com/photo-1492496913980-501348b61469?ixlib=rb-1.2.1&ixid=MnwxMjA3fDB8MHxwaG90by1wYWdlfHx8fGVufDB8fHx8&auto=format&fit=crop&w=387&q=80",
        "name": "Prepare soil",
        "time": "10",
        "break_time": "10"
    },
    {
        "id": "633461c54075a4275d6c5df2",
        "image": "https://images.unsplash.com/photo-1641320201668-1b2bedb4a066?ixlib=rb-1.2.1&ixid=MnwxMjA3fDB8MHxwaG90by1wYWdlfHx8fGVufDB8fHx8&auto=format&fit=crop&w=387&q=80",
        "name": "Plant the tree",
        "time": "15 Minute",
        "break_time": "20"
    },
    {
        "id": "633461c57e07b52146b73089",
        "image": "https://images.unsplash.com/photo-1515150144380-bca9f1650ed9?ixlib=rb-1.2.1&ixid=MnwxMjA3fDB8MHxwaG90by1wYWdlfHx8fGVufDB8fHx8&auto=format&fit=crop&w=387&q=80",
        "name": "Water the trees",
        "time": "23",
        "break_time": "30"
    },
    {
        "id": "633461c5002b090df15e13e5",
        "image": "https://images.unsplash.com/photo-1558906307-1a1c52b5ac8a?ixlib=rb-1.2.1&ixid=MnwxMjA3fDB8MHxwaG90by1wYWdlfHx8fGVufDB8fHx8&auto=format&fit=crop&w=872&q=80",
        "name": "Use Fertilizer",
        "time": "5",
        "break_time": "40"
    },
    {
        "id": "633461c5df4e4922b3279024",
        "image": "https://images.unsplash.com/photo-1599719839704-0092318dd800?ixlib=rb-1.2.1&ixid=MnwxMjA3fDB8MHxwaG90by1wYWdlfHx8fGVufDB8fHx8&auto=format&fit=crop&w=464&q=80",
        "name": "Use Insecticide",
        "time": "40",
        "break_time": "60"
    },
    {
        "id": "633461c51d563d90e1d96bcb",
        "image": "https://images.unsplash.com/photo-1624699859241-37c86968dd61?ixlib=rb-1.2.1&ixid=MnwxMjA3fDB8MHxzZWFyY2h8Mzh8fGhhcnZlc3QlMjBmcm9tJTIwZnJ1aXR8ZW58MHx8MHx8&auto=format&fit=crop&w=500&q=60",
        "name": "Harvest from plant",
        "time": "55",
        "break_time": "60"
    }
]